pdpm/__init__.py
pdpm/_open.py
pdpm/create.py
pdpm/remove.py
pdpm/set_path.py
pdpm/show.py
pdpm/start.py
pdpm-0.1.1.dist-info/LICENSE
pdpm-0.1.1.dist-info/METADATA
pdpm-0.1.1.dist-info/WHEEL
pdpm-0.1.1.dist-info/entry_points.txt
pdpm-0.1.1.dist-info/top_level.txt
pdpm-0.1.1.dist-info/RECORD
