Metadata-Version: 2.1
Name: pdpm
Version: 0.1.1
Summary: Python project manager
Home-page: https://github.com/Okirshen/pdpm
Author: Ofri Kirshen
Author-email: okirshen@gmail.com
License: MIT
Platform: UNKNOWN
Requires-Dist: Click
